pd_stepper/__init__.py
pd_stepper/controller.py
pd_stepper/pd_stepper.py
pd_stepper/serial_port.py
pd_stepper/status.py
pd_stepper/utils.py
py_pd_stepper-0.1.1.dist-info/LICENSE
py_pd_stepper-0.1.1.dist-info/METADATA
py_pd_stepper-0.1.1.dist-info/WHEEL
py_pd_stepper-0.1.1.dist-info/RECORD
