Metadata-Version: 2.3
Name: py-pd-stepper
Version: 0.1.1
Summary: 
Author: Thiago Meyer
Author-email: tiagmey@gmail.com
Requires-Python: >=3.10,<4.0
Classifier: Programming Language :: Python :: 3
Classifier: Programming Language :: Python :: 3.10
Classifier: Programming Language :: Python :: 3.11
Classifier: Programming Language :: Python :: 3.12
Classifier: Programming Language :: Python :: 3.13
Requires-Dist: pyserial (>=3.5,<4.0)
